tests/__init__.py
tests/test_algorithms.py
whynot_estimators/__init__.py
whynot_estimators/__main__.py
whynot_estimators/bart.py
whynot_estimators/causal_forest.py
whynot_estimators/deconfounder.py
whynot_estimators/doubleml.py
whynot_estimators/estimator.py
whynot_estimators/ip_weighting.py
whynot_estimators/matching.py
whynot_estimators/rlearner_mlp.py
whynot_estimators/rlearner_xbg.py
whynot_estimators/slearner_linear.py
whynot_estimators/tmle.py
whynot_estimators/utils.py
whynot_estimators-0.11.0.dist-info/LICENSE.txt
whynot_estimators-0.11.0.dist-info/METADATA
whynot_estimators-0.11.0.dist-info/WHEEL
whynot_estimators-0.11.0.dist-info/top_level.txt
whynot_estimators-0.11.0.dist-info/RECORD
