Metadata-Version: 2.1
Name: whynot-estimators
Version: 0.11.0
Summary: Companion package to whynot: A collection of causal estimators.
Home-page: UNKNOWN
Author: John Miller
Author-email: miller_john@berkeley.edu
License: UNKNOWN
Platform: UNKNOWN
Classifier: Programming Language :: Python :: 3
Classifier: License :: OSI Approved :: MIT License
Classifier: Operating System :: MacOS
Classifier: Operating System :: POSIX
Requires-Python: >=3.6
Requires-Dist: cython
Requires-Dist: numpy
Requires-Dist: pandas
Requires-Dist: sklearn
Requires-Dist: whynot
Requires-Dist: tzlocal
